MANIFEST.in
README.rst
setup.cfg
setup.py
tests/Testing.md
tests/test_cli.py
tests/commands/secure_support.py
tests/commands/test_cluster_health.py
tests/commands/test_cluster_state.py
tests/commands/test_cluster_stats.py
tests/commands/test_indices_stats.py
tests/commands/test_just_indices_stats.py
tests/commands/test_just_nodes_stats.py
tests/commands/test_nodes_hotthreads.py
tests/commands/test_nodes_info.py
tests/commands/test_nodes_stats.py
tests/conf/elasticsearch.yml
tests/conf/logging.yml
tests/conf/sg_action_groups.yml
tests/conf/sg_config.yml
tests/conf/sg_internal_users.yml
tests/conf/sg_roles.yml
tests/conf/sg_roles_mapping.yml
tests/setup/setup_run_all.sh
tests/setup/sg_init.sh
watches/__init__.py
watches/cli.py
watches/commands/__init__.py
watches/commands/base.py
watches/commands/cluster_health.py
watches/commands/cluster_state.py
watches/commands/cluster_stats.py
watches/commands/indices_stats.py
watches/commands/just_indices_stats.py
watches/commands/just_nodes_stats.py
watches/commands/nodes_hotthreads.py
watches/commands/nodes_info.py
watches/commands/nodes_stats.py
watches/util/ESClientProducer.py
watches/util/__init__.py