Metadata-Version: 1.1
Name: watches
Version: 1.0.3
Summary: CLI tool to pull statistics from Elasticsearch.
Home-page: https://github.com/ViaQ/watches-cli
Author: Lukas Vlcek
Author-email: lukas.vlcek@gmail.com
License: ASL2
Download-URL: https://github.com/ViaQ/watches-cli/archive/v1.0.3.tar.gz
Keywords: cli,elasticsearch
Platform: UNKNOWN
Classifier: Intended Audience :: Developers
Classifier: Topic :: Utilities
Classifier: License :: OSI Approved :: Apache Software License
Classifier: Natural Language :: English
Classifier: Operating System :: OS Independent
Classifier: Programming Language :: Python :: 2.7
Classifier: Programming Language :: Python :: 3.5
